sharepoint_auth
