Metadata-Version: 1.1
Name: django-sharepoint-auth
Version: 1.1
Summary: Authenticate users using SharePoint.
Home-page: https://bitbucket.org/nextscreenlabs/django-sharepoint-auth
Author: Jason Christa
Author-email: jason@zeitcode.com
License: UNKNOWN
Platform: UNKNOWN
Classifier: Environment :: Web Environment
Classifier: License :: OSI Approved :: BSD License
Classifier: Framework :: Django
Classifier: Programming Language :: Python
